{
	"credit": "Made with Blockbench",
	"textures": {
		"0": "qlrp/mic",
		"particle": "qlrp/mic"
	},
	"elements": [
		{
			"from": [6.75, 0, 7],
			"to": [8.75, 9, 9],
			"faces": {
				"north": {"uv": [0, 0, 2, 9], "texture": "#0"},
				"east": {"uv": [2, 0, 4, 9], "texture": "#0"},
				"south": {"uv": [4, 0, 6, 9], "texture": "#0"},
				"west": {"uv": [6, 0, 8, 9], "texture": "#0"},
				"up": {"uv": [8, 15, 6, 13], "texture": "#0"},
				"down": {"uv": [16, 12, 14, 14], "texture": "#0"}
			}
		},
		{
			"from": [6.25, 10, 6.5],
			"to": [9.25, 14, 9.5],
			"faces": {
				"north": {"uv": [12, 4, 15, 8], "texture": "#0"},
				"east": {"uv": [8, 12, 11, 16], "texture": "#0"},
				"south": {"uv": [12, 8, 15, 12], "texture": "#0"},
				"west": {"uv": [11, 12, 14, 16], "texture": "#0"},
				"up": {"uv": [3, 16, 0, 13], "texture": "#0"},
				"down": {"uv": [6, 13, 3, 16], "texture": "#0"}
			}
		},
		{
			"from": [5.75, 6, 6],
			"to": [9.75, 10, 10],
			"faces": {
				"north": {"uv": [8, 0, 12, 4], "texture": "#0"},
				"east": {"uv": [8, 4, 12, 8], "texture": "#0"},
				"south": {"uv": [8, 8, 12, 12], "texture": "#0"},
				"west": {"uv": [0, 9, 4, 13], "texture": "#0"},
				"up": {"uv": [8, 13, 4, 9], "texture": "#0"},
				"down": {"uv": [16, 0, 12, 4], "texture": "#0"}
			}
		}
	],
	"display": {
		"thirdperson_righthand": {
			"rotation": [0, 162, 0],
			"translation": [-0.5, 2.5, 2.25]
		},
		"thirdperson_lefthand": {
			"rotation": [0, 162, 0],
			"translation": [-0.5, 2.5, 2.25]
		},
		"firstperson_righthand": {
			"rotation": [156.67, 6.79, 164.65],
			"translation": [0, 3.5, -0.75],
			"scale": [0.75977, 0.75977, 0.75977]
		},
		"firstperson_lefthand": {
			"rotation": [156.67, 6.79, 164.65],
			"translation": [0, 3.5, -0.75],
			"scale": [0.75977, 0.75977, 0.75977]
		},
		"ground": {
			"rotation": [90, 0, 0],
			"translation": [0, 5, 0]
		},
		"gui": {
			"rotation": [29, 155, -30],
			"scale": [0.91602, 0.91602, 0.91602]
		},
		"fixed": {
			"rotation": [64, 0, -180],
			"translation": [0, -6, -6.5],
			"scale": [2.13672, 2.13672, 2.13672]
		}
	}
}